dotadevkit/__init__.py
dotadevkit/cli/__init__.py
dotadevkit/cli/cli.py
dotadevkit/cli/convert.py
dotadevkit/cli/evaluate.py
dotadevkit/cli/merge.py
dotadevkit/cli/split.py
dotadevkit/cli/visualise.py
dotadevkit/evaluate/__init__.py
dotadevkit/evaluate/task1.py
dotadevkit/evaluate/task2.py
dotadevkit/misc/__init__.py
dotadevkit/misc/dota_utils.py
dotadevkit/ops/CocoConvert.py
dotadevkit/ops/ImgSplit.py
dotadevkit/ops/ResultMerge.py
dotadevkit/ops/SplitOnlyImage.py
dotadevkit/ops/Visualise.py
dotadevkit/ops/__init__.py
dotadevkit/polyiou/__init__.py
dotadevkit/polyiou/_polyiou.cpython-38-darwin.so
dotadevkit/polyiou/polyiou.py
poly_nms_gpu/__init__.py
poly_nms_gpu/nms_wrapper.py
poly_nms_gpu/poly_nms_test.py
poly_nms_gpu/setup.py
dotadevkit-1.3.0.dist-info/METADATA
dotadevkit-1.3.0.dist-info/WHEEL
dotadevkit-1.3.0.dist-info/entry_points.txt
dotadevkit-1.3.0.dist-info/top_level.txt
dotadevkit-1.3.0.dist-info/RECORD
