Metadata-Version: 2.1
Name: dotadevkit
Version: 1.3.0
Summary: DOTA Devkit CLI
Home-page: https://github.com/ashnair1/dotadevkit
Author: Ashwin Nair
Author-email: ash1995@gmail.com
License: UNKNOWN
Platform: UNKNOWN
Classifier: Programming Language :: Python
Classifier: Programming Language :: Python :: 3.6
Classifier: Programming Language :: Python :: 3.7
Classifier: Programming Language :: Python :: 3.8
Classifier: Programming Language :: Python :: 3.9
Classifier: Programming Language :: Python :: Implementation :: CPython
Requires-Python: >=3.6
